minj/__init__.py
minj/cron_log.py
minj/main.py
minj/metrics_log.py
minj/sleep_log.py
minj-0.0.1.dist-info/LICENSE
minj-0.0.1.dist-info/METADATA
minj-0.0.1.dist-info/WHEEL
minj-0.0.1.dist-info/entry_points.txt
minj-0.0.1.dist-info/top_level.txt
minj-0.0.1.dist-info/RECORD
