Metadata-Version: 2.1
Name: minj
Version: 0.0.1
Summary: Minimalist Journal on CLI
Home-page: https://github.com/guilhermelowa/minj
Author: Guilherme Lowa
Author-email: guilhermelowa@protonmail.com
License: UNKNOWN
Platform: UNKNOWN
Classifier: Programming Language :: Python :: 3
Classifier: License :: OSI Approved :: MIT License
Classifier: Operating System :: OS Independent
Requires-Python: >=3.6
